xps_lib/__init__-Copy1.py
xps_lib/__init__.py
xps_lib/file.py
xps_lib/analysis/__init__.py
xps_lib/analysis/reporting.py
xps_lib/analysis/residual_analysis.py
xps_lib/calibration/__init__.py
xps_lib/calibration/calibrator.py
xps_lib/constraints/__init__.py
xps_lib/constraints/base.py
xps_lib/constraints/constraints_new.py
xps_lib/constraints/single.py
xps_lib/constraints/standard.py
xps_lib/core/__init__.py
xps_lib/core/dataset.py
xps_lib/core/workflow.py
xps_lib/elements/__init__.py
xps_lib/elements/reference_table.py
xps_lib/elements/suggester.py
xps_lib/fitting/__init__.py
xps_lib/fitting/background.py
xps_lib/fitting/fitter.py
xps_lib/io/__init__.py
xps_lib/io/constants.py
xps_lib/io/loader.py
xps_lib/lineshapes/__init__.py
xps_lib/lineshapes/base.py
xps_lib/lineshapes/custom.py
xps_lib/lineshapes/standard.py
xps_lib/peakfinding/__init__.py
xps_lib/peakfinding/finder.py
xps_lib/quantification/__init__.py
xps_lib/quantification/quantifier.py
xps_lib/regions/__init__.py
xps_lib/regions/elementregion.py
xps_lib/regions/fittingregion.py
xps_lib/regions/peakstack.py
xps_lib/regions/reference.py
xps_lib/utils/__init__.py
xps_lib/utils/export.py
xps_lib/utils/result_formatter.py
xps_lib/utils/validators.py
xps_lib/utils/visualization.py
xps_lib-1.0.2.dist-info/METADATA
xps_lib-1.0.2.dist-info/WHEEL
xps_lib-1.0.2.dist-info/top_level.txt
xps_lib-1.0.2.dist-info/RECORD
