Metadata-Version: 2.4
Name: xps_lib
Version: 1.0.2
Home-page: https://gitlab.tuwien.ac.at/iap/aip/anp/surface-analysis/xps-analysis
Author: Viktoria Rotheneder, Lara Farkas, Camil x, Richard W. van Nieuwenhoven, Kai Schwenzfeier, Markus Valtiner
Author-email: viktoria.rotheneder@tuwien.ac.at
Project-URL: Homepage, https://researchdata.tuwien.ac.at/uploads/3c1r2-8nq63
Keywords: todo
Classifier: Programming Language :: Python :: 3
Classifier: License :: OSI Approved :: MIT License
Classifier: Operating System :: OS Independent
Requires-Python: >=3.1
Requires-Dist: matplotlib>=3.5.1
Requires-Dist: NumPy>=1.26
Requires-Dist: pandas>=2.2.3
Requires-Dist: scipy>=1.15.3
Dynamic: author
Dynamic: author-email
Dynamic: classifier
Dynamic: description
Dynamic: description-content-type
Dynamic: home-page
Dynamic: keywords
Dynamic: project-url
Dynamic: requires-dist
Dynamic: requires-python
